gumo/__init__.py
gumo/task_emulator/__init__.py
gumo/task_emulator/_configuration.py
gumo/task_emulator/bind.py
gumo/task_emulator/application/__init__.py
gumo/task_emulator/application/task/__init__.py
gumo/task_emulator/application/task/encoder.py
gumo/task_emulator/application/task/repository.py
gumo/task_emulator/domain/__init__.py
gumo/task_emulator/domain/configuration/__init__.py
gumo/task_emulator/infrastructure/__init__.py
gumo/task_emulator/infrastructure/execute_service/__init__.py
gumo/task_emulator/infrastructure/mapper/__init__.py
gumo/task_emulator/infrastructure/repository/__init__.py
gumo/task_emulator/presentation/__init__.py
gumo/task_emulator/presentation/cli/__init__.py
gumo/task_emulator/presentation/cli/worker/__init__.py
gumo/task_emulator/presentation/restapi/__init__.py
gumo/task_emulator/presentation/ui/__init__.py
gumo/task_emulator/presentation/ui/template/detail.html
gumo/task_emulator/presentation/ui/template/index.html
gumo/task_emulator/presentation/ui/template/layout.html
gumo_task_emulator-0.3.0.dist-info/LICENSE
gumo_task_emulator-0.3.0.dist-info/METADATA
gumo_task_emulator-0.3.0.dist-info/WHEEL
gumo_task_emulator-0.3.0.dist-info/top_level.txt
gumo_task_emulator-0.3.0.dist-info/RECORD
