Metadata-Version: 2.1
Name: gumo-task-emulator
Version: 0.3.0
Summary: Gumo Task Emulator Library
Home-page: https://github.com/gumo-py/gumo-task-emulator
Author: Gumo Project Team
Author-email: gumo-py@googlegroups.com
License: UNKNOWN
Platform: UNKNOWN
Classifier: Programming Language :: Python :: 3
Classifier: License :: OSI Approved :: MIT License
Classifier: Operating System :: OS Independent
Requires-Dist: gumo-core (>=0.1.0)
Requires-Dist: gumo-datastore (>=0.2.0)
Requires-Dist: gumo-task (>=0.3.2)
Requires-Dist: Flask (>=1.0.2)
